causticsnupy/__init__.py
causticsnupy/caustics.py
causticsnupy/hierarchical_clustering.py
causticsnupy/kde.py
causticsnupy-1.0.4.dist-info/METADATA
causticsnupy-1.0.4.dist-info/WHEEL
causticsnupy-1.0.4.dist-info/licenses/LICENSE
causticsnupy-1.0.4.dist-info/RECORD
