Metadata-Version: 2.4
Name: causticsnupy
Version: 1.0.4
Summary: Python package for determining cluster members using caustic technique.
Project-URL: Homepage, https://github.com/woodykang/CausticSNUpy
Author-email: Wooseok Kang <woodykang@snu.ac.kr>
License-File: LICENSE
Classifier: License :: OSI Approved :: MIT License
Classifier: Operating System :: OS Independent
Classifier: Programming Language :: Python :: 3
Requires-Python: >=3.8
Requires-Dist: astropy>=4.3.1
Requires-Dist: numpy>=1.20.3
Requires-Dist: scikit-image>=0.17.2
Requires-Dist: scipy>=1.7.1
